odoo/addons/sale_order_lot_selection_price/README.rst
odoo/addons/sale_order_lot_selection_price/__init__.py
odoo/addons/sale_order_lot_selection_price/__manifest__.py
odoo/addons/sale_order_lot_selection_price/i18n/es.po
odoo/addons/sale_order_lot_selection_price/i18n/it.po
odoo/addons/sale_order_lot_selection_price/i18n/sale_order_lot_selection_price.pot
odoo/addons/sale_order_lot_selection_price/models/__init__.py
odoo/addons/sale_order_lot_selection_price/models/product_product.py
odoo/addons/sale_order_lot_selection_price/models/sale_order_line.py
odoo/addons/sale_order_lot_selection_price/models/stock_lot.py
odoo/addons/sale_order_lot_selection_price/readme/CONTRIBUTORS.md
odoo/addons/sale_order_lot_selection_price/readme/DESCRIPTION.md
odoo/addons/sale_order_lot_selection_price/readme/USAGE.md
odoo/addons/sale_order_lot_selection_price/static/description/icon.png
odoo/addons/sale_order_lot_selection_price/static/description/index.html
odoo/addons/sale_order_lot_selection_price/tests/__init__.py
odoo/addons/sale_order_lot_selection_price/tests/test_sale_order_lot_selection_price.py
odoo/addons/sale_order_lot_selection_price/views/stock_lot_views.xml
odoo_addon_sale_order_lot_selection_price-18.0.1.0.0.5.dist-info/METADATA
odoo_addon_sale_order_lot_selection_price-18.0.1.0.0.5.dist-info/WHEEL
odoo_addon_sale_order_lot_selection_price-18.0.1.0.0.5.dist-info/top_level.txt
odoo_addon_sale_order_lot_selection_price-18.0.1.0.0.5.dist-info/RECORD
