Metadata-Version: 2.1
Name: odoo-addon-sale_order_lot_selection_price
Version: 18.0.1.0.0.5
Requires-Python: >=3.10
Requires-Dist: odoo-addon-sale_order_lot_selection==18.0.*
Requires-Dist: odoo==18.0.*
Summary: Sale Order Lot Selection Price
Home-page: https://github.com/OCA/sale-workflow
License: AGPL-3
Author: Tecnativa, Odoo Community Association (OCA)
Author-email: support@odoo-community.org
Classifier: Programming Language :: Python
Classifier: Framework :: Odoo
Classifier: Framework :: Odoo :: 18.0
Classifier: License :: OSI Approved :: GNU Affero General Public License v3
